{
  "id": "2b9fbb47-cd3b-4f80-84ec-fc79a65e6f60",
  "prevId": "8c7fb74f-0d9c-4f9f-8852-f230b0046590",
  "version": "7",
  "dialect": "postgresql",
  "tables": {
    "public.application_responses": {
      "name": "application_responses",
      "schema": "",
      "columns": {
        "id": {
          "name": "id",
          "type": "serial",
          "primaryKey": true,
          "notNull": true
        },
        "application_id": {
          "name": "application_id",
          "type": "integer",
          "primaryKey": false,
          "notNull": true
        },
        "custom_field_id": {
          "name": "custom_field_id",
          "type": "integer",
          "primaryKey": false,
          "notNull": true
        },
        "response_value": {
          "name": "response_value",
          "type": "text",
          "primaryKey": false,
          "notNull": false
        }
      },
      "indexes": {},
      "foreignKeys": {
        "application_responses_application_id_applications_id_fk": {
          "name": "application_responses_application_id_applications_id_fk",
          "tableFrom": "application_responses",
          "tableTo": "applications",
          "columnsFrom": [
            "application_id"
          ],
          "columnsTo": [
            "id"
          ],
          "onDelete": "no action",
          "onUpdate": "no action"
        },
        "application_responses_custom_field_id_custom_fields_id_fk": {
          "name": "application_responses_custom_field_id_custom_fields_id_fk",
          "tableFrom": "application_responses",
          "tableTo": "custom_fields",
          "columnsFrom": [
            "custom_field_id"
          ],
          "columnsTo": [
            "id"
          ],
          "onDelete": "no action",
          "onUpdate": "no action"
        }
      },
      "compositePrimaryKeys": {},
      "uniqueConstraints": {},
      "policies": {},
      "checkConstraints": {},
      "isRLSEnabled": false
    },
    "public.applications": {
      "name": "applications",
      "schema": "",
      "columns": {
        "id": {
          "name": "id",
          "type": "serial",
          "primaryKey": true,
          "notNull": true
        },
        "user_id": {
          "name": "user_id",
          "type": "integer",
          "primaryKey": false,
          "notNull": true
        },
        "program_id": {
          "name": "program_id",
          "type": "integer",
          "primaryKey": false,
          "notNull": true
        },
        "status": {
          "name": "status",
          "type": "status",
          "typeSchema": "public",
          "primaryKey": false,
          "notNull": true,
          "default": "'pending'"
        },
        "applied_at": {
          "name": "applied_at",
          "type": "timestamp",
          "primaryKey": false,
          "notNull": true,
          "default": "now()"
        },
        "reviewed_at": {
          "name": "reviewed_at",
          "type": "timestamp",
          "primaryKey": false,
          "notNull": false
        },
        "certificate_issued_at": {
          "name": "certificate_issued_at",
          "type": "timestamp",
          "primaryKey": false,
          "notNull": false
        }
      },
      "indexes": {},
      "foreignKeys": {
        "applications_user_id_users_id_fk": {
          "name": "applications_user_id_users_id_fk",
          "tableFrom": "applications",
          "tableTo": "users",
          "columnsFrom": [
            "user_id"
          ],
          "columnsTo": [
            "id"
          ],
          "onDelete": "no action",
          "onUpdate": "no action"
        },
        "applications_program_id_programs_id_fk": {
          "name": "applications_program_id_programs_id_fk",
          "tableFrom": "applications",
          "tableTo": "programs",
          "columnsFrom": [
            "program_id"
          ],
          "columnsTo": [
            "id"
          ],
          "onDelete": "no action",
          "onUpdate": "no action"
        }
      },
      "compositePrimaryKeys": {},
      "uniqueConstraints": {},
      "policies": {},
      "checkConstraints": {},
      "isRLSEnabled": false
    },
    "public.custom_fields": {
      "name": "custom_fields",
      "schema": "",
      "columns": {
        "id": {
          "name": "id",
          "type": "serial",
          "primaryKey": true,
          "notNull": true
        },
        "program_id": {
          "name": "program_id",
          "type": "integer",
          "primaryKey": false,
          "notNull": true
        },
        "label": {
          "name": "label",
          "type": "varchar(200)",
          "primaryKey": false,
          "notNull": true
        },
        "field_type": {
          "name": "field_type",
          "type": "field_type",
          "typeSchema": "public",
          "primaryKey": false,
          "notNull": true
        },
        "options": {
          "name": "options",
          "type": "text",
          "primaryKey": false,
          "notNull": false
        },
        "is_required": {
          "name": "is_required",
          "type": "boolean",
          "primaryKey": false,
          "notNull": true,
          "default": true
        },
        "step_number": {
          "name": "step_number",
          "type": "integer",
          "primaryKey": false,
          "notNull": true,
          "default": 3
        },
        "order_index": {
          "name": "order_index",
          "type": "integer",
          "primaryKey": false,
          "notNull": true,
          "default": 0
        }
      },
      "indexes": {},
      "foreignKeys": {
        "custom_fields_program_id_programs_id_fk": {
          "name": "custom_fields_program_id_programs_id_fk",
          "tableFrom": "custom_fields",
          "tableTo": "programs",
          "columnsFrom": [
            "program_id"
          ],
          "columnsTo": [
            "id"
          ],
          "onDelete": "no action",
          "onUpdate": "no action"
        }
      },
      "compositePrimaryKeys": {},
      "uniqueConstraints": {},
      "policies": {},
      "checkConstraints": {},
      "isRLSEnabled": false
    },
    "public.programs": {
      "name": "programs",
      "schema": "",
      "columns": {
        "id": {
          "name": "id",
          "type": "serial",
          "primaryKey": true,
          "notNull": true
        },
        "admin_id": {
          "name": "admin_id",
          "type": "integer",
          "primaryKey": false,
          "notNull": true
        },
        "type": {
          "name": "type",
          "type": "program_type",
          "typeSchema": "public",
          "primaryKey": false,
          "notNull": true
        },
        "title": {
          "name": "title",
          "type": "varchar(200)",
          "primaryKey": false,
          "notNull": true
        },
        "description": {
          "name": "description",
          "type": "text",
          "primaryKey": false,
          "notNull": true
        },
        "category": {
          "name": "category",
          "type": "varchar(100)",
          "primaryKey": false,
          "notNull": false
        },
        "location": {
          "name": "location",
          "type": "varchar(200)",
          "primaryKey": false,
          "notNull": false
        },
        "mode": {
          "name": "mode",
          "type": "mode",
          "typeSchema": "public",
          "primaryKey": false,
          "notNull": true
        },
        "deadline": {
          "name": "deadline",
          "type": "timestamp",
          "primaryKey": false,
          "notNull": true
        },
        "start_date": {
          "name": "start_date",
          "type": "date",
          "primaryKey": false,
          "notNull": false
        },
        "end_date": {
          "name": "end_date",
          "type": "date",
          "primaryKey": false,
          "notNull": false
        },
        "stipend": {
          "name": "stipend",
          "type": "varchar(100)",
          "primaryKey": false,
          "notNull": false
        },
        "duration": {
          "name": "duration",
          "type": "varchar(100)",
          "primaryKey": false,
          "notNull": false
        },
        "required_skills": {
          "name": "required_skills",
          "type": "text",
          "primaryKey": false,
          "notNull": false
        },
        "is_active": {
          "name": "is_active",
          "type": "boolean",
          "primaryKey": false,
          "notNull": true,
          "default": true
        },
        "created_at": {
          "name": "created_at",
          "type": "timestamp",
          "primaryKey": false,
          "notNull": true,
          "default": "now()"
        }
      },
      "indexes": {},
      "foreignKeys": {
        "programs_admin_id_users_id_fk": {
          "name": "programs_admin_id_users_id_fk",
          "tableFrom": "programs",
          "tableTo": "users",
          "columnsFrom": [
            "admin_id"
          ],
          "columnsTo": [
            "id"
          ],
          "onDelete": "no action",
          "onUpdate": "no action"
        }
      },
      "compositePrimaryKeys": {},
      "uniqueConstraints": {},
      "policies": {},
      "checkConstraints": {},
      "isRLSEnabled": false
    },
    "public.users": {
      "name": "users",
      "schema": "",
      "columns": {
        "id": {
          "name": "id",
          "type": "serial",
          "primaryKey": true,
          "notNull": true
        },
        "clerk_id": {
          "name": "clerk_id",
          "type": "varchar(255)",
          "primaryKey": false,
          "notNull": true
        },
        "name": {
          "name": "name",
          "type": "varchar(100)",
          "primaryKey": false,
          "notNull": true
        },
        "email": {
          "name": "email",
          "type": "varchar(150)",
          "primaryKey": false,
          "notNull": true
        },
        "role": {
          "name": "role",
          "type": "role",
          "typeSchema": "public",
          "primaryKey": false,
          "notNull": true,
          "default": "'user'"
        },
        "profile_photo": {
          "name": "profile_photo",
          "type": "varchar(255)",
          "primaryKey": false,
          "notNull": false
        },
        "bio": {
          "name": "bio",
          "type": "text",
          "primaryKey": false,
          "notNull": false
        },
        "created_at": {
          "name": "created_at",
          "type": "timestamp",
          "primaryKey": false,
          "notNull": true,
          "default": "now()"
        }
      },
      "indexes": {},
      "foreignKeys": {},
      "compositePrimaryKeys": {},
      "uniqueConstraints": {
        "users_clerk_id_unique": {
          "name": "users_clerk_id_unique",
          "nullsNotDistinct": false,
          "columns": [
            "clerk_id"
          ]
        },
        "users_email_unique": {
          "name": "users_email_unique",
          "nullsNotDistinct": false,
          "columns": [
            "email"
          ]
        }
      },
      "policies": {},
      "checkConstraints": {},
      "isRLSEnabled": false
    }
  },
  "enums": {
    "public.field_type": {
      "name": "field_type",
      "schema": "public",
      "values": [
        "text",
        "textarea",
        "url",
        "file",
        "select"
      ]
    },
    "public.mode": {
      "name": "mode",
      "schema": "public",
      "values": [
        "online",
        "offline",
        "hybrid"
      ]
    },
    "public.program_type": {
      "name": "program_type",
      "schema": "public",
      "values": [
        "event",
        "internship"
      ]
    },
    "public.role": {
      "name": "role",
      "schema": "public",
      "values": [
        "user",
        "admin"
      ]
    },
    "public.status": {
      "name": "status",
      "schema": "public",
      "values": [
        "pending",
        "accepted",
        "rejected",
        "completed"
      ]
    }
  },
  "schemas": {},
  "sequences": {},
  "roles": {},
  "policies": {},
  "views": {},
  "_meta": {
    "columns": {},
    "schemas": {},
    "tables": {}
  }
}